enum_field.py
django_enum_field-0.2.dist-info/DESCRIPTION.rst
django_enum_field-0.2.dist-info/METADATA
django_enum_field-0.2.dist-info/RECORD
django_enum_field-0.2.dist-info/WHEEL
django_enum_field-0.2.dist-info/metadata.json
django_enum_field-0.2.dist-info/top_level.txt
