Metadata-Version: 2.0
Name: django-enum-field
Version: 0.2
Summary: UNKNOWN
Home-page: UNKNOWN
Author: UNKNOWN
Author-email: UNKNOWN
License: UNKNOWN
Platform: UNKNOWN
Requires-Dist: python-enumeration
Requires-Dist: Django (>=1.8)
